README.rst
peeweedbevolve.py
setup.py
peewee_db_evolve.egg-info/PKG-INFO
peewee_db_evolve.egg-info/SOURCES.txt
peewee_db_evolve.egg-info/dependency_links.txt
peewee_db_evolve.egg-info/requires.txt
peewee_db_evolve.egg-info/top_level.txt