Metadata-Version: 1.1
Name: peewee-db-evolve
Version: 0.6.8
Summary: Schema Evolution for Peewee
Home-page: https://github.com/keredson/peewee-db-evolve
Author: Derek Anderson
Author-email: public@kered.org
License: UNKNOWN
Platform: UNKNOWN
Classifier: Development Status :: 5 - Production/Stable
Classifier: Intended Audience :: Developers
Classifier: License :: OSI Approved :: GNU Lesser General Public License v3 (LGPLv3)
Classifier: Operating System :: OS Independent
Classifier: Programming Language :: Python
Classifier: Programming Language :: Python :: 3
